mcp_headgym_base/__init__.py
mcp_headgym_base/main.py
mcp_headgym_base-0.1.6.dist-info/METADATA
mcp_headgym_base-0.1.6.dist-info/WHEEL
mcp_headgym_base-0.1.6.dist-info/entry_points.txt
mcp_headgym_base-0.1.6.dist-info/top_level.txt
mcp_headgym_base-0.1.6.dist-info/RECORD
