Metadata-Version: 2.2
Name: mcp-headgym-base
Version: 0.1.6
Summary: Provides utlities for accessing HeadGym experts
Requires-Python: >=3.11
Requires-Dist: mcp[cli]>=1.3.0
